Metadata-Version: 2.1
Name: fctr
Version: 1.0
Summary: Code to solve for factors in a quadratic equation
Home-page: UNKNOWN
Author: Daniel Akhabue
Author-email: akdaniel0009@gmail.com
License: UNKNOWN
Platform: UNKNOWN
